limited/__init__.py
limited/async_limiter.py
limited/base_limiter.py
limited/py.typed
limited/sync_limiter.py
limited-0.1.0.dist-info/LICENSE
limited-0.1.0.dist-info/METADATA
limited-0.1.0.dist-info/WHEEL
limited-0.1.0.dist-info/top_level.txt
limited-0.1.0.dist-info/RECORD
