Metadata-Version: 2.1
Name: limited
Version: 0.1.0
Summary: Advanced rate limiting in Python
Author-email: Alon Krymgand <me@alon.kr>
Project-URL: Homepage, https://github.com/RealA10N/limited
Requires-Python: >=3.11
License-File: LICENSE
